LICENSE
beancount_syspath/__init__.py
beancount_syspath/append.py
beancount_syspath/plugin.py
beancount_syspath/prepend.py
beancount_syspath-0.2.1.dist-info/LICENSE
beancount_syspath-0.2.1.dist-info/WHEEL
beancount_syspath-0.2.1.dist-info/METADATA
beancount_syspath-0.2.1.dist-info/RECORD
