Metadata-Version: 2.1
Name: beancount-syspath
Version: 0.2.1
Summary: Manipulate sys.path within the beancount file
Home-page: https://github.com/Aetf/beancount-syspath
License: MIT
Keywords: beancount,plugin,syspath
Author: Aetf
Author-email: aetf@unlimited-code.works
Requires-Python: >=3.6,<4.0
Classifier: Development Status :: 5 - Production/Stable
Classifier: Environment :: Plugins
Classifier: Intended Audience :: Financial and Insurance Industry
Classifier: License :: OSI Approved :: MIT License
Classifier: Operating System :: OS Independent
Classifier: Programming Language :: Python :: 3
Classifier: Programming Language :: Python :: 3 :: Only
Classifier: Programming Language :: Python :: 3.6
Classifier: Programming Language :: Python :: 3.7
Classifier: Programming Language :: Python :: 3.8
Classifier: Topic :: Utilities
Project-URL: Repository, https://github.com/Aetf/beancount-syspath
